scratch_verify/__init__.py
scratch_verify-1.0.1.dist-info/METADATA
scratch_verify-1.0.1.dist-info/WHEEL
scratch_verify-1.0.1.dist-info/license
scratch_verify-1.0.1.dist-info/top_level.txt
scratch_verify-1.0.1.dist-info/RECORD
