Metadata-Version: 2.1
Name: scratch-verify
Version: 1.0.1
Summary: Verify the ownership of a Scratch account.
Home-page: https://github.com/Richienb/scratch-verify-python
Author: Richie Bendall
Author-email: richiebendall@gmail.com
License: MIT
Keywords: scratch verify account ownership user
Platform: UNKNOWN
Classifier: Development Status :: 5 - Production/Stable
Classifier: Intended Audience :: End Users/Desktop
Classifier: License :: OSI Approved :: MIT License
Classifier: Natural Language :: English
Classifier: Operating System :: OS Independent
Classifier: Programming Language :: Python
Classifier: Typing :: Typed
Requires-Python: >=3.6
Requires-Dist: requests (~=2.25.1)
